buildabot/__init__.py
buildabot/__main__.py
buildabot/bot.py
buildabot/event_handler.py
buildabot/logger.py
buildabot/module.py
buildabot/module_manager.py
buildabot/typer.py
buildabot/utils.py
BuildABot-2.0.4.dist-info/METADATA
BuildABot-2.0.4.dist-info/WHEEL
BuildABot-2.0.4.dist-info/top_level.txt
BuildABot-2.0.4.dist-info/RECORD
