Metadata-Version: 2.1
Name: BuildABot
Version: 2.0.4
Summary: Build a Dicord bot with ease and flexibility
Home-page: https://gitlab.com/artex-development/bot_framework
Author: AL_1
License: UNKNOWN
Platform: UNKNOWN
Classifier: Development Status :: 4 - Beta
Classifier: Intended Audience :: Developers
Classifier: Natural Language :: English
Classifier: Operating System :: OS Independent
Classifier: Programming Language :: Python :: 3.6
Classifier: Programming Language :: Python :: 3.7
Classifier: Topic :: Internet
Classifier: Topic :: Software Development :: Libraries
Classifier: Topic :: Software Development :: Libraries :: Python Modules
Classifier: Topic :: Utilities
Requires-Python: >=3.6
Requires-Dist: discord.py
Requires-Dist: pytz
Requires-Dist: aiohttp
